LICENSE
README.md
pyproject.toml
setup.py
src/aipilot/__init__.py
src/aipilot.egg-info/PKG-INFO
src/aipilot.egg-info/SOURCES.txt
src/aipilot.egg-info/dependency_links.txt
src/aipilot.egg-info/requires.txt
src/aipilot.egg-info/top_level.txt
src/aipilot/pckgLogger/__init__.py
src/aipilot/tf/__init__.py
src/aipilot/tf/callbacks.py
src/aipilot/tf/devices.py
src/aipilot/tf/eval.py
src/aipilot/tf/cv/__init__.py
src/aipilot/tf/cv/data_prep.py
src/aipilot/tf/cv/gradcam.py
src/aipilot/utils/__init__.py
src/aipilot/utils/utils.py