Metadata-Version: 2.1
Name: aipilot
Version: 0.0.0-dev8
Summary: A python library to support and speed up Machine Learning and Deep Learning Model Training and Evaluation
Home-page: https://github.com/Hassi34/aipilot
Author: Hasanain Mehmood
Author-email: hasanain@aicaliber.com
License: MIT
Project-URL: Bug Tracker, https://github.com/Hassi34/aipilot/issues
Platform: UNKNOWN
Classifier: Development Status :: 5 - Production/Stable
Classifier: Intended Audience :: Developers
Classifier: Programming Language :: Python :: 3.7
Classifier: Programming Language :: Python :: 3.8
Classifier: Programming Language :: Python :: 3.9
Classifier: Programming Language :: Python :: 3.10
Classifier: License :: OSI Approved :: MIT License
Classifier: Topic :: Scientific/Engineering :: Artificial Intelligence
Classifier: Operating System :: OS Independent
Requires-Python: >=3.7
License-File: LICENSE
